grep_func/__init__.py
grep_func/grep_func.py
grep_func-1.0.2.dist-info/LICENSE
grep_func-1.0.2.dist-info/METADATA
grep_func-1.0.2.dist-info/WHEEL
grep_func-1.0.2.dist-info/top_level.txt
grep_func-1.0.2.dist-info/RECORD
