Metadata-Version: 2.1
Name: grep-func
Version: 1.0.2
Summary: A python package to grep 'functions' within modules
Home-page: https://github.com/karry3775/grep_func
License: UNKNOWN
Platform: UNKNOWN
Classifier: Programming Language :: Python :: 2
Classifier: License :: OSI Approved :: MIT License
Classifier: Operating System :: OS Independent
